geojson2vt/__init__.py
geojson2vt/clip.py
geojson2vt/convert.py
geojson2vt/feature.py
geojson2vt/geojson2vt.py
geojson2vt/simplify.py
geojson2vt/tile.py
geojson2vt/transform.py
geojson2vt/utils.py
geojson2vt/wrap.py
geojson2vt-0.0.1.dist-info/LICENSE
geojson2vt-0.0.1.dist-info/METADATA
geojson2vt-0.0.1.dist-info/WHEEL
geojson2vt-0.0.1.dist-info/top_level.txt
geojson2vt-0.0.1.dist-info/RECORD
